django_filters-stubs/__init__.pyi
django_filters-stubs/compat.pyi
django_filters-stubs/conf.pyi
django_filters-stubs/constants.pyi
django_filters-stubs/exceptions.pyi
django_filters-stubs/fields.pyi
django_filters-stubs/filters.pyi
django_filters-stubs/filterset.pyi
django_filters-stubs/models.pyi
django_filters-stubs/utils.pyi
django_filters-stubs/views.pyi
django_filters-stubs/widgets.pyi
django_filters-stubs/rest_framework/__init__.pyi
django_filters-stubs/rest_framework/backends.pyi
django_filters-stubs/rest_framework/filters.pyi
django_filters-stubs/rest_framework/filterset.pyi
django_filter_stubs-0.1.3.dist-info/LICENSE.txt
django_filter_stubs-0.1.3.dist-info/METADATA
django_filter_stubs-0.1.3.dist-info/WHEEL
django_filter_stubs-0.1.3.dist-info/top_level.txt
django_filter_stubs-0.1.3.dist-info/RECORD
